capture/__init__.py
capture/capture.py
capture/adapters/__init__.py
capture/adapters/base.py
capture/adapters/email.py
capture/templates/alert.html
capture_errors-0.0.3.dist-info/LICENSE
capture_errors-0.0.3.dist-info/METADATA
capture_errors-0.0.3.dist-info/WHEEL
capture_errors-0.0.3.dist-info/top_level.txt
capture_errors-0.0.3.dist-info/RECORD
