Metadata-Version: 2.1
Name: capture-errors
Version: 0.0.3
Summary: Python package that captures exceptions and notify them
Home-page: UNKNOWN
Author: Ashish Garg
Author-email: ashish.garg@linux.com
License: UNKNOWN
Keywords: python,exceptions,errors
Platform: UNKNOWN
Classifier: Development Status :: 3 - Alpha
Classifier: Intended Audience :: Developers
Classifier: License :: OSI Approved :: Apache Software License
Classifier: Programming Language :: Python :: 2
Classifier: Programming Language :: Python :: 3
Classifier: Operating System :: OS Independent
Classifier: Operating System :: Microsoft :: Windows
Requires-Dist: Jinja2 (>=3.0)
Provides-Extra: requests
